opensense/__init__.py
opensense/csi_module.py
opensense/utils.py
opensense-0.0.1.dist-info/LICENSE.txt
opensense-0.0.1.dist-info/METADATA
opensense-0.0.1.dist-info/WHEEL
opensense-0.0.1.dist-info/top_level.txt
opensense-0.0.1.dist-info/RECORD
