Metadata-Version: 2.1
Name: opensense
Version: 0.0.1
Summary: A python library for wireless sensing
Home-page: https://github.com/xyanchen/WiFi-CSI-Sensing-Benchmark
Author: Jianfei
Author-email: yang0478@e.ntu.edu.sg
Requires-Python: >=3.6
License-File: LICENSE.txt
Requires-Dist: torch
Requires-Dist: numpy
Requires-Dist: scipy
Requires-Dist: tsmoothie
